[
  {
    "hideFromTouchBar": true,
    "ankiExtraAnswerField": "",
    "id": "0CD6C67D-F4F1-45FD-9534-A6ED7B79AECF",
    "actionValue": "",
    "batteryFullIcon": "",
    "nhkNavOnLeft": true,
    "ankiCombineFurigana": false,
    "ankiShowAgain": true,
    "nhkFuriganaFontSize": 6.5,
    "ankiTouchBarAudioField": "Audio",
    "ankiBoldColorHex": "#FFD60A",
    "textColorHex": "#FFFFFF",
    "animationSpeed": 0.2,
    "ankiIsMuted": false,
    "ankiHardColorHex": "#E58019",
    "type": "NHK Easy News",
    "batteryLowIcon": "",
    "ankiQuestionTextOffset": 0,
    "ankiFuriganaVerticalOffset": 0,
    "ankiDeckSettings": {},
    "ankiAgainColorHex": "#E53333",
    "monitorType": "CPU Usage",
    "ankiTrimText": true,
    "ankiTextMaxWidth": 250,
    "ankiAnswerTextOffset": 0,
    "ankiAudioOnlyOnAnswer": true,
    "ankiQuestionField": "Front",
    "ankiShowRemainingCounts": false,
    "batteryFullThreshold": 85,
    "ankiFuriganaQuestionTextOffset": 0,
    "ankiEasyColorHex": "#3380E5",
    "actionType": "None",
    "ankiShowHard": true,
    "ankiDeckName": "",
    "ankiGoodColorHex": "#19B24C",
    "backgroundColorHex": "#1E1E24",
    "fontSize": 18,
    "batteryLowThreshold": 20,
    "batteryDisplayType": "Image or Animation",
    "ankiAnswerField": "Back",
    "isHidden": false,
    "ankiShowEasy": true,
    "volumeSliderWidth": 150,
    "longPressActionType": "None",
    "iconName": "newspaper.fill",
    "customWidth": 740,
    "ankiAudioField": "Audio",
    "animationType": "Walking Cat 🐱🐾",
    "title": "NHK Easy News",
    "ankiFuriganaTextOffset": 0,
    "customGifPath": "",
    "batteryNormalIcon": "",
    "showSeconds": true,
    "ankiShowGood": true,
    "nhkFuriganaColorHex": "#FFFFFF",
    "volumeShowIcon": true,
    "longPressActionValue": "",
    "brightnessButtonSize": 16,
    "ankiExtraQuestionField": "",
    "batteryChargingIcon": "",
    "ankiFuriganaFontSize": 0
  },
  {
    "hideFromTouchBar": false,
    "ankiExtraAnswerField": "Sentence Meaning",
    "id": "081183CA-CD87-43EA-9A89-9051F0B11248",
    "actionValue": "",
    "batteryFullIcon": "",
    "nhkNavOnLeft": false,
    "ankiCombineFurigana": true,
    "ankiShowAgain": true,
    "nhkFuriganaFontSize": 0,
    "ankiTouchBarAudioField": "Word Audio",
    "ankiBoldColorHex": "#00FA92",
    "textColorHex": "#FFFFFF",
    "animationSpeed": 0.2,
    "ankiIsMuted": false,
    "ankiHardColorHex": "#E58019",
    "type": "Anki Review",
    "batteryLowIcon": "",
    "ankiQuestionTextOffset": 5,
    "ankiFuriganaVerticalOffset": -2,
    "ankiDeckSettings": {
      "日本語N4練習": {
        "questionField": "",
        "answerField": "",
        "audioField": "",
        "extraQuestionField": "",
        "extraAnswerField": "",
        "touchBarAudioField": ""
      },
      "Kaishi 1.5k": {
        "questionField": "Word,Sentence",
        "answerField": "Word Reading,Sentence Furigana",
        "audioField": "Sentence Audio",
        "extraQuestionField": "Word Meaning",
        "extraAnswerField": "Sentence Meaning",
        "touchBarAudioField": "Word Audio"
      }
    },
    "ankiAgainColorHex": "#E53333",
    "monitorType": "CPU Usage",
    "ankiTrimText": true,
    "ankiTextMaxWidth": 580,
    "ankiAnswerTextOffset": 5,
    "ankiAudioOnlyOnAnswer": true,
    "ankiQuestionField": "Word,Sentence",
    "ankiShowRemainingCounts": true,
    "batteryFullThreshold": 85,
    "ankiFuriganaQuestionTextOffset": 0,
    "ankiEasyColorHex": "#3380E5",
    "actionType": "None",
    "ankiShowHard": false,
    "ankiDeckName": "Kaishi 1.5k",
    "ankiGoodColorHex": "#19B24C",
    "backgroundColorHex": "#1E1E24",
    "fontSize": 20,
    "batteryLowThreshold": 20,
    "batteryDisplayType": "Image or Animation",
    "ankiAnswerField": "Word Reading,Sentence Furigana",
    "isHidden": false,
    "ankiShowEasy": false,
    "volumeSliderWidth": 150,
    "longPressActionType": "None",
    "iconName": "rectangle.stack.fill",
    "customWidth": 0,
    "ankiAudioField": "Sentence Audio",
    "animationType": "Walking Cat 🐱🐾",
    "title": "Anki Review",
    "ankiFuriganaTextOffset": 3,
    "customGifPath": "",
    "batteryNormalIcon": "",
    "showSeconds": true,
    "ankiShowGood": true,
    "nhkFuriganaColorHex": "#FFFFFF",
    "volumeShowIcon": true,
    "longPressActionValue": "",
    "brightnessButtonSize": 16,
    "ankiExtraQuestionField": "Word Meaning",
    "batteryChargingIcon": "",
    "ankiFuriganaFontSize": 8
  },
  {
    "hideFromTouchBar": false,
    "ankiExtraAnswerField": "",
    "id": "D8C24FB5-602D-44D2-A8DF-D3C7132CA06F",
    "actionValue": "",
    "batteryFullIcon": "",
    "nhkNavOnLeft": false,
    "ankiCombineFurigana": false,
    "ankiShowAgain": true,
    "nhkFuriganaFontSize": 0,
    "ankiTouchBarAudioField": "Audio",
    "ankiBoldColorHex": "#FFD60A",
    "textColorHex": "#FFFFFF",
    "animationSpeed": 0.2,
    "ankiIsMuted": false,
    "ankiHardColorHex": "#E58019",
    "type": "Brightness Controls",
    "batteryLowIcon": "",
    "ankiQuestionTextOffset": 0,
    "ankiFuriganaVerticalOffset": 0,
    "ankiDeckSettings": {},
    "ankiAgainColorHex": "#E53333",
    "monitorType": "CPU Usage",
    "ankiTrimText": true,
    "ankiTextMaxWidth": 250,
    "ankiAnswerTextOffset": 0,
    "ankiAudioOnlyOnAnswer": true,
    "ankiQuestionField": "Front",
    "ankiShowRemainingCounts": false,
    "batteryFullThreshold": 85,
    "ankiFuriganaQuestionTextOffset": 0,
    "ankiEasyColorHex": "#3380E5",
    "actionType": "None",
    "ankiShowHard": true,
    "ankiDeckName": "",
    "ankiGoodColorHex": "#19B24C",
    "backgroundColorHex": "#1E1E24",
    "fontSize": 12,
    "batteryLowThreshold": 20,
    "batteryDisplayType": "Image or Animation",
    "ankiAnswerField": "Back",
    "isHidden": false,
    "ankiShowEasy": true,
    "volumeSliderWidth": 150,
    "longPressActionType": "None",
    "iconName": "sun.max.fill",
    "customWidth": 0,
    "ankiAudioField": "Audio",
    "animationType": "Walking Cat 🐱🐾",
    "title": "Brightness Controls",
    "ankiFuriganaTextOffset": 0,
    "customGifPath": "",
    "batteryNormalIcon": "",
    "showSeconds": true,
    "ankiShowGood": true,
    "nhkFuriganaColorHex": "#FFFFFF",
    "volumeShowIcon": true,
    "longPressActionValue": "",
    "brightnessButtonSize": 30,
    "ankiExtraQuestionField": "",
    "batteryChargingIcon": "",
    "ankiFuriganaFontSize": 0
  },
  {
    "hideFromTouchBar": false,
    "ankiExtraAnswerField": "",
    "id": "B7FE22B2-099D-4F27-A7CE-9D30B6BB1A10",
    "actionValue": "",
    "batteryFullIcon": "",
    "nhkNavOnLeft": false,
    "ankiCombineFurigana": false,
    "ankiShowAgain": true,
    "nhkFuriganaFontSize": 0,
    "ankiTouchBarAudioField": "Audio",
    "ankiBoldColorHex": "#FFD60A",
    "textColorHex": "#FFFFFF",
    "animationSpeed": 0.2,
    "ankiIsMuted": false,
    "ankiHardColorHex": "#E58019",
    "type": "Volume Slider",
    "batteryLowIcon": "",
    "ankiQuestionTextOffset": 0,
    "ankiFuriganaVerticalOffset": 0,
    "ankiDeckSettings": {},
    "ankiAgainColorHex": "#E53333",
    "monitorType": "CPU Usage",
    "ankiTrimText": true,
    "ankiTextMaxWidth": 250,
    "ankiAnswerTextOffset": 0,
    "ankiAudioOnlyOnAnswer": true,
    "ankiQuestionField": "Front",
    "ankiShowRemainingCounts": false,
    "batteryFullThreshold": 85,
    "ankiFuriganaQuestionTextOffset": 0,
    "ankiEasyColorHex": "#3380E5",
    "actionType": "None",
    "ankiShowHard": true,
    "ankiDeckName": "",
    "ankiGoodColorHex": "#19B24C",
    "backgroundColorHex": "#1E1E24",
    "fontSize": 12,
    "batteryLowThreshold": 20,
    "batteryDisplayType": "Image or Animation",
    "ankiAnswerField": "Back",
    "isHidden": false,
    "ankiShowEasy": true,
    "volumeSliderWidth": 130,
    "longPressActionType": "None",
    "iconName": "speaker.wave.3.fill",
    "customWidth": 0,
    "ankiAudioField": "Audio",
    "animationType": "Walking Cat 🐱🐾",
    "title": "Volume Slider",
    "ankiFuriganaTextOffset": 0,
    "customGifPath": "",
    "batteryNormalIcon": "",
    "showSeconds": true,
    "ankiShowGood": true,
    "nhkFuriganaColorHex": "#FFFFFF",
    "volumeShowIcon": false,
    "longPressActionValue": "",
    "brightnessButtonSize": 16,
    "ankiExtraQuestionField": "",
    "batteryChargingIcon": "",
    "ankiFuriganaFontSize": 0
  },
  {
    "hideFromTouchBar": false,
    "ankiExtraAnswerField": "",
    "id": "2F0B195B-EE6C-457E-9F09-FE0F93CC1091",
    "actionValue": "",
    "batteryFullIcon": "\/Users\/halim13\/Downloads\/miku\/full (1).gif",
    "nhkNavOnLeft": false,
    "ankiCombineFurigana": false,
    "ankiShowAgain": true,
    "nhkFuriganaFontSize": 0,
    "ankiTouchBarAudioField": "Audio",
    "ankiBoldColorHex": "#FFD60A",
    "textColorHex": "#FFFFFF",
    "animationSpeed": 0.2,
    "ankiIsMuted": false,
    "ankiHardColorHex": "#E58019",
    "type": "System Monitor",
    "batteryLowIcon": "\/Users\/halim13\/Downloads\/miku\/anime-hatsune-miku-cry.gif",
    "ankiQuestionTextOffset": 0,
    "ankiFuriganaVerticalOffset": 0,
    "ankiDeckSettings": {},
    "ankiAgainColorHex": "#E53333",
    "monitorType": "Battery Level",
    "ankiTrimText": true,
    "ankiTextMaxWidth": 250,
    "ankiAnswerTextOffset": 0,
    "ankiAudioOnlyOnAnswer": true,
    "ankiQuestionField": "Front",
    "ankiShowRemainingCounts": false,
    "batteryFullThreshold": 85,
    "ankiFuriganaQuestionTextOffset": 0,
    "ankiEasyColorHex": "#3380E5",
    "actionType": "None",
    "ankiShowHard": true,
    "ankiDeckName": "",
    "ankiGoodColorHex": "#19B24C",
    "backgroundColorHex": "#1E1E24",
    "fontSize": 12,
    "batteryLowThreshold": 20,
    "batteryDisplayType": "Image or Animation",
    "ankiAnswerField": "Back",
    "isHidden": false,
    "ankiShowEasy": true,
    "volumeSliderWidth": 150,
    "longPressActionType": "None",
    "iconName": "battery.100",
    "customWidth": 0,
    "ankiAudioField": "Audio",
    "animationType": "Walking Cat 🐱🐾",
    "title": "battery",
    "ankiFuriganaTextOffset": 0,
    "customGifPath": "",
    "batteryNormalIcon": "\/Users\/halim13\/Downloads\/miku\/charging.gif",
    "showSeconds": true,
    "ankiShowGood": true,
    "nhkFuriganaColorHex": "#FFFFFF",
    "volumeShowIcon": true,
    "longPressActionValue": "",
    "brightnessButtonSize": 16,
    "ankiExtraQuestionField": "",
    "batteryChargingIcon": "\/Users\/halim13\/Downloads\/miku\/hatsune-miku-charging.gif",
    "ankiFuriganaFontSize": 0
  }
]
